Kuat/__init__.py
nyako-0.1.0.dist-info/METADATA
nyako-0.1.0.dist-info/WHEEL
nyako-0.1.0.dist-info/top_level.txt
nyako-0.1.0.dist-info/RECORD
